upassist/__init__.py
upassist/__main__.py
upassist/config.py
upassist/errors.py
upassist/version.py
upassist/client/__init__.py
upassist/client/_async.py
upassist/client/_sync.py
upassist/client/abstract.py
upassist/entities/__init__.py
upassist/entities/base.py
upassist/entities/heartbeat/__init__.py
upassist/entities/heartbeat/heartbeat.py
upassist/entities/heartbeat/schemas.py
upassist/entities/logs/__init__.py
upassist/entities/logs/logs.py
upassist/entities/logs/schemas.py
upassist/schemas/__init__.py
upassist/schemas/base.py
upassist/utils/__init__.py
upassist/utils/attributes.py
upassist/utils/passwords.py
upassist-0.0.8.dist-info/METADATA
upassist-0.0.8.dist-info/WHEEL
upassist-0.0.8.dist-info/licenses/LICENSE
upassist-0.0.8.dist-info/RECORD
