Metadata-Version: 2.4
Name: upassist
Version: 0.0.8
Summary: Official Upasist Cloud API python SDK
Project-URL: Homepage, https://github.com/upassist-cloud/upassist-python
Project-URL: Issues, https://github.com/upassist-cloud/upassist-python/issues
Project-URL: Documentation, https://upassist-python.upassist.cloud
Author-email: michael7nightingale <suslanchikmopl@gmail.com>
License-Expression: MIT
License-File: LICENSE
Classifier: Operating System :: OS Independent
Classifier: Programming Language :: Python :: 3
Requires-Python: >=3.10
Requires-Dist: pydantic-extra-types>=2.1.0
Requires-Dist: pydantic>=2.11.3
Provides-Extra: async
Requires-Dist: aiohttp>=3.11.16; extra == 'async'
Provides-Extra: docs
Requires-Dist: mkdocs-gen-files>=0.5.0; extra == 'docs'
Requires-Dist: mkdocs-literate-nav>=0.6.1; extra == 'docs'
Requires-Dist: mkdocs-material>=9.5.3; extra == 'docs'
Requires-Dist: mkdocs-section-index>=0.3.8; extra == 'docs'
Requires-Dist: mkdocs>=1.5.3; extra == 'docs'
Requires-Dist: mkdocstrings[python]>=0.24.0; extra == 'docs'
Provides-Extra: sync
Requires-Dist: requests>=2.32.3; extra == 'sync'
Provides-Extra: uv
Requires-Dist: black>=25.1.0; extra == 'uv'
Requires-Dist: isort>=6.0.1; extra == 'uv'
Requires-Dist: mypy>=1.15.0; extra == 'uv'
Requires-Dist: ruff>=0.11.5; extra == 'uv'
